fau_colors/__init__.py
fau_colors/_utils.py
fau_colors/fonts.py
fau_colors/v2019.py
fau_colors/v2021.py
fau_colors/v2024.py
fau_colors-1.10.1.dist-info/METADATA
fau_colors-1.10.1.dist-info/WHEEL
fau_colors-1.10.1.dist-info/licenses/LICENSE
fau_colors-1.10.1.dist-info/RECORD
