Metadata-Version: 2.4
Name: fau_colors
Version: 1.10.1
Summary: The official colors of FAU as matplotlib/seaborn colormaps
Project-URL: Homepage, https://github.com/mad-lab-fau/fau_colors
Project-URL: Repository, https://github.com/mad-lab-fau/fau_colors
Author-email: Robert Richer <robert.richer@fau.de>, Arne Küderle <arne.kuederle@fau.de>
License-Expression: MIT
License-File: LICENSE
Requires-Python: <3.13,>=3.9
Requires-Dist: matplotlib>=3.6.3
Requires-Dist: seaborn>=0.11.2
